Workbook

Sheet Inputs
A1: INFOSYS — STOCK VALUATION MODEL
A2: Units: ₹ crore unless otherwise stated
A4: Model Assumptions
A6: Assumption | B6: FY2027 | C6: FY2028 | D6: FY2029 | E6: FY2030 | F6: FY2031
A7: Revenue Growth | B7: 0.03 | C7: 0.05 | D7: 0.06 | E7: 0.06 | F7: 0.06
A8: EBITDA Margin | B8: 0.235 | C8: 0.235 | D8: 0.235 | E8: 0.235 | F8: 0.235
A9: D&A / Revenue | B9: 0.0275 | C9: 0.0275 | D9: 0.0275 | E9: 0.0275 | F9: 0.0275
A10: Tax Rate | B10: 0.25 | C10: 0.25 | D10: 0.25 | E10: 0.25 | F10: 0.25
A11: Capex / Revenue | B11: 0.015 | C11: 0.015 | D11: 0.015 | E11: 0.015 | F11: 0.015
A12: Change in NWC / Revenue | B12: 0.015 | C12: 0.015 | D12: 0.015 | E12: 0.015 | F12: 0.015
A13: Risk-Free Rate | B13: 0.0698
A14: Beta | B14: 0.5
A15: Equity Risk Premium | B15: 0.0781
A16: Cost of Debt | B16: 0
A17: Terminal Growth Rate | B17: 0.04
A18: Current Share Price | B18: 1036.5
A19: Cash & Investments | B19: 43075
A20: Shares Outstanding (crore) | B20: 405.82

Sheet Historicals
A1: INFOSYS — HISTORICAL FINANCIALS
A2: Units: ₹ crore unless otherwise stated
A4: Particulars | B4: FY2022 | C4: FY2023 | D4: FY2024 | E4: FY2025 | F4: FY2026
A5: Revenue | B5: 121641 | C5: 146767 | D5: 153670 | E5: 162990 | F5: 178650
A6: EBITDA | B6: 31491 | C6: 35130 | D6: 36425 | E6: 39236 | F6: 41156
A7: EBIT | B7: 28015 | C7: 30905 | D7: 31747 | E7: 34424 | F7: 36254
A8: Net Income | B8: 22146 | C8: 24108 | D8: 26248 | E8: 26750 | F8: 29474
A9: D&A | B9: 3476 | C9: 4225 | D9: 4678 | E9: 4812 | F9: 4902
A10: Capex | B10: 2161 | C10: 2579 | D10: 2201 | E10: 2237 | F10: 2727
A11: Change in NWC | B11: 1183 | C11: 6503 | D11: 5162 | E11: 605 | F11: 2306
A12: Total Debt | B12: 0 | C12: 0 | D12: 0 | E12: 0 | F12: 0
A13: Cash | B13: 17472 | C13: 12173 | D13: 14786 | E13: 24455 | F13: 22201
A14: Shares Outstanding(crore) | B14: 419.3 | C14: 413.64 | D14: 415.09 | E14: 414.36 | F14: 404.69
A16: Historical Ratios
A17: Revenue Growth | C17: =C5/B5-1 -> 0.20655864 | D17: =D5/C5-1 -> 0.047033734 | E17: =E5/D5-1 -> 0.060649444 | F17: =F5/E5-1 -> 0.096079514
A18: EBITDA Margin | B18: =B6/B5 -> 0.25888475 | C18: =C6/C5 -> 0.23935898 | D18: =D6/D5 -> 0.2370339 | E18: =E6/E5 -> 0.24072642 | F18: =F6/F5 -> 0.23037224
A19: EBIT Margin | B19: =B7/B5 -> 0.23030886 | C19: =C7/C5 -> 0.21057186 | D19: =D7/D5 -> 0.20659205 | E19: =E7/E5 -> 0.21120314 | F19: =F7/F5 -> 0.20293311
A20: Capex / Revenue | B20: =B10/B5 -> 0.017765392 | C20: =C10/C5 -> 0.01757207 | D20: =D10/D5 -> 0.0143229 | E20: =E10/E5 -> 0.013724768 | F20: =F10/F5 -> 0.015264484
A21: Change in NWC / Revenue | B21: =B11/B5 -> 0.0097253393 | C21: =C11/C5 -> 0.044308325 | D21: =D11/D5 -> 0.033591462 | E21: =E11/E5 -> 0.0037118842 | F21: =F11/F5 -> 0.012907921

Sheet Forecast
A1: INFOSYS — FORECAST
A2: Units: ₹ crore unless otherwise stated
B4: FY2027 | C4: FY2028 | D4: FY2029 | E4: FY2030 | F4: FY2031
A5: Revenue Growth | B5: =Inputs!B7 -> 0.03 | C5: =Inputs!C7 -> 0.05 | D5: =Inputs!D7 -> 0.06 | E5: =Inputs!E7 -> 0.06 | F5: =Inputs!F7 -> 0.06
A6: Revenue | B6: =Historicals!F5*(1+B5) -> 184009.5 | C6: =B6*(1+C5) -> 193209.98 | D6: =C6*(1+D5) -> 204802.57 | E6: =D6*(1+E5) -> 217090.73 | F6: =E6*(1+F5) -> 230116.17
A7: EBITDA | B7: =B6*B8 -> 43242.232 | C7: =C6*C8 -> 45404.344 | D7: =D6*D8 -> 48128.605 | E7: =E6*E8 -> 51016.321 | F7: =F6*F8 -> 54077.3
A8: EBITDA Margin | B8: =Inputs!B8 -> 0.235 | C8: =Inputs!C8 -> 0.235 | D8: =Inputs!D8 -> 0.235 | E8: =Inputs!E8 -> 0.235 | F8: =Inputs!F8 -> 0.235
A9: D&A | B9: =B6*Inputs!B9 -> 5060.2613 | C9: =C6*Inputs!C9 -> 5313.2743 | D9: =D6*Inputs!D9 -> 5632.0708 | E9: =E6*Inputs!E9 -> 5969.995 | F9: =F6*Inputs!F9 -> 6328.1947
A10: EBIT | B10: =B7-B9 -> 38181.971 | C10: =C7-C9 -> 40091.07 | D10: =D7-D9 -> 42496.534 | E10: =E7-E9 -> 45046.326 | F10: =F7-F9 -> 47749.106
A11: EBIT Margin | B11: =B10/B6 -> 0.2075 | C11: =C10/C6 -> 0.2075 | D11: =D10/D6 -> 0.2075 | E11: =E10/E6 -> 0.2075 | F11: =F10/F6 -> 0.2075
A12: Tax Rate | B12: =Inputs!B10 -> 0.25 | C12: =Inputs!C10 -> 0.25 | D12: =Inputs!D10 -> 0.25 | E12: =Inputs!E10 -> 0.25 | F12: =Inputs!F10 -> 0.25
A13: NOPAT | B13: =B10*(1-B12) -> 28636.478 | C13: =C10*(1-C12) -> 30068.302 | D13: =D10*(1-D12) -> 31872.401 | E13: =E10*(1-E12) -> 33784.745 | F13: =F10*(1-F12) -> 35811.829
A14: Capex | B14: =B6*Inputs!B11 -> 2760.1425 | C14: =C6*Inputs!C11 -> 2898.1496 | D14: =D6*Inputs!D11 -> 3072.0386 | E14: =E6*Inputs!E11 -> 3256.3609 | F14: =F6*Inputs!F11 -> 3451.7426
A15: Change in NWC | B15: =B6*(Inputs!B12) -> 2760.1425 | C15: =C6*(Inputs!C12) -> 2898.1496 | D15: =D6*(Inputs!D12) -> 3072.0386 | E15: =E6*(Inputs!E12) -> 3256.3609 | F15: =F6*(Inputs!F12) -> 3451.7426
A16: FCFF | B16: =B13+B9-B14-B15 -> 28176.455 | C16: =C13+C9-C14-C15 -> 29585.277 | D16: =D13+D9-D14-D15 -> 31360.394 | E16: =E13+E9-E14-E15 -> 33242.018 | F16: =F13+F9-F14-F15 -> 35236.539

Sheet DCF
A1: INFOSYS — DCF VALUATION
A2: Units: ₹ crore unless otherwise stated
B4: FY2027 | C4: FY2028 | D4: FY2029 | E4: FY2030 | F4: FY2031
A5: FCFF | B5: =Forecast!B16 -> 28176.455 | C5: =Forecast!C16 -> 29585.277 | D5: =Forecast!D16 -> 31360.394 | E5: =Forecast!E16 -> 33242.018 | F5: =Forecast!F16 -> 35236.539
A6: Discount Period | B6: 1 | C6: 2 | D6: 3 | E6: 4 | F6: 5
A7: Discount Factor | B7: =1/(1+$B$9)^B6 -> 0.90183523 | C7: =1/(1+$B$9)^C6 -> 0.81330679 | D7: =1/(1+$B$9)^D6 -> 0.73346872 | E7: =1/(1+$B$9)^E6 -> 0.66146794 | F7: =1/(1+$B$9)^F6 -> 0.59653509
A8: PV of FCFF | B8: =B5*B7 -> 25410.52 | C8: =C5*C7 -> 24061.907 | D8: =D5*D7 -> 23001.868 | E8: =E5*E7 -> 21988.529 | F8: =F5*F7 -> 21019.832
A9: WACC | B9: =B33 -> 0.10885
A10: Terminal Growth Rate | B10: =Inputs!B17 -> 0.04
A11: Terminal Value | B11: =F5*(1+B10)/(B33-B10) -> 532258.54
A12: PV of Terminal Value | B12: =B11*F7 -> 317510.9
A13: Enterprise Value | B13: =SUM(B8:F8)+B12 -> 432993.55
A14: Cash & Investments | B14: =Inputs!B19 -> 43075
A15: Debt | B15: =Historicals!F12 -> 0
A16: Equity Value | B16: =B13+B14-B15 -> 476068.55
A17: Shares Outstanding(crore) | B17: =Inputs!B20 -> 405.82
A18: Intrinsic Value / Share | B18: =B16/B17 -> 1173.1027
A19: Current Share Price | B19: =Inputs!B18 -> 1036.5
A20: Upside / (Downside) | B20: =B18/B19-1 -> 0.13179231
A24: Risk-Free Rate | B24: =Inputs!B13 -> 0.0698
A25: Beta | B25: =Inputs!B14 -> 0.5
A26: Equity Risk Premium | B26: =Inputs!B15 -> 0.0781
A27: Cost of Equity | B27: =B24+B25*B26 -> 0.10885
A28: Cost of Debt | B28: =Inputs!B16 -> 0
A29: Market Value of Equity | B29: =Inputs!B18*Inputs!B20 -> 420632.43
A30: Debt | B30: 0
A31: Equity Weight | B31: =B29/(B30+B29) -> 1
A32: Debt Weight | B32: =B30/(B30+B29) -> 0
A33: WACC | B33: =B31*B27+B32*B28*(1-Inputs!B10) -> 0.10885
A36: DCF Sensitivity — Intrinsic Value / Share
A37: WACC \ Terminal Growth | B37: 0.03 | C37: 0.04 | D37: 0.05
A38: =B33-1% -> 0.09885 | B38: {=(SUMPRODUCT($B$5:$F$5,1/(1+$A38)^$B$6:$F$6)+($F$5*(1+B$37)/($A38-B$37))/(1+$A38)^$F$6+$B$14-$B$15)/$B$17} -> 1209.1006 | C38: {=(SUMPRODUCT($B$5:$F$5,1/(1+$A38)^$B$6:$F$6)+($F$5*(1+C$37)/($A38-C$37))/(1+$A38)^$F$6+$B$14-$B$15)/$B$17} -> 1356.0797 | D38: {=(SUMPRODUCT($B$5:$F$5,1/(1+$A38)^$B$6:$F$6)+($F$5*(1+D$37)/($A38-D$37))/(1+$A38)^$F$6+$B$14-$B$15)/$B$17} -> 1563.2346
A39: =B33 -> 0.10885 | B39: {=(SUMPRODUCT($B$5:$F$5,1/(1+$A39)^$B$6:$F$6)+($F$5*(1+B$37)/($A39-B$37))/(1+$A39)^$F$6+$B$14-$B$15)/$B$17} -> 1067.3083 | C39: {=(SUMPRODUCT($B$5:$F$5,1/(1+$A39)^$B$6:$F$6)+($F$5*(1+C$37)/($A39-C$37))/(1+$A39)^$F$6+$B$14-$B$15)/$B$17} -> 1173.1027 | D39: {=(SUMPRODUCT($B$5:$F$5,1/(1+$A39)^$B$6:$F$6)+($F$5*(1+D$37)/($A39-D$37))/(1+$A39)^$F$6+$B$14-$B$15)/$B$17} -> 1314.8511
A40: =B33+1% -> 0.11885 | B40: {=(SUMPRODUCT($B$5:$F$5,1/(1+$A40)^$B$6:$F$6)+($F$5*(1+B$37)/($A40-B$37))/(1+$A40)^$F$6+$B$14-$B$15)/$B$17} -> 957.49371 | C40: {=(SUMPRODUCT($B$5:$F$5,1/(1+$A40)^$B$6:$F$6)+($F$5*(1+C$37)/($A40-C$37))/(1+$A40)^$F$6+$B$14-$B$15)/$B$17} -> 1036.5822 | D40: {=(SUMPRODUCT($B$5:$F$5,1/(1+$A40)^$B$6:$F$6)+($F$5*(1+D$37)/($A40-D$37))/(1+$A40)^$F$6+$B$14-$B$15)/$B$17} -> 1138.6448

Sheet Comps
A1: INFOSYS — COMPARABLE COMPANIES ANALYSIS
A2: Valuation Date: 10-Sep-2026
A3: Units: ₹ crore unless otherwise stated
A5: Company | B5: Infosys | C5: TCS | D5: HCLTech | E5: Wipro | F5: Tech Mahindra
A6: Share Price | B6: =Inputs!B18 -> 1036.5 | C6: 2199.4 | D6: 1207 | E6: 166.3 | F6: 1525.8
A7: Market Capitalization | B7: =DCF!B29 -> 420632.43 | C7: 797000 | D7: 327000 | E7: 164000 | F7: 135000
A8: Enterprise Value | B8: 399455 | C8: 764862 | D8: 307000 | E8: 146000 | F8: 129000
A9: LTM Revenue | B9: 184582 | C9: 275859 | D9: 134374 | E9: 94968 | F9: 59176
A10: LTM EBITDA | B10: 42622 | C10: 74079 | D10: 27492 | E10: 18211 | F10: 9841
A11: LTM Net Income | B11: 30288 | C11: 49799 | D11: 18142 | E11: 13219 | F11: 5135
A12: P/E | B12: =B7/B11 -> 13.887759 | C12: =C7/C11 -> 16.004337 | D12: =D7/D11 -> 18.024474 | E12: =E7/E11 -> 12.406385 | F12: =F7/F11 -> 26.290166
A13: EV/EBITDA | B13: =B8/B10 -> 9.3720379 | C13: =C8/C10 -> 10.32495 | D13: =D8/D10 -> 11.166885 | E13: =E8/E10 -> 8.0171325 | F13: =F8/F10 -> 13.108424
A15: Peer Median P/E | B15: =MEDIAN(C12:F12) -> 17.014406
A16: Peer Median EV/EBITDA | B16: =MEDIAN(C13:F13) -> 10.745918
A18: Relative Valuation — Implied Infosys Value
A19: Metric | B19: Peer Multiple | C19: Infosys Metric | D19: Implied Value | E19: Implied Price / Share
A20: P/E | B20: =B15 -> 17.014406 | C20: =B11 -> 30288 | D20: =B20*C20 -> 515332.31 | E20: =D20/DCF!B17 -> 1269.8544
A21: EV/EBITDA | B21: =B16 -> 10.745918 | C21: =B10 -> 42622 | D21: =B21*C21 -> 458012.5
A23: EV/EBITDA Equity Value Bridge
A24: Implied Enterprise Value | B24: =D21 -> 458012.5
A25: Cash & Investments | B25: =Inputs!B19 -> 43075
A26: Debt | B26: =Historicals!F12 -> 0
A27: Implied Equity Value | B27: =B24+B25-B26 -> 501087.5
A28: Shares Outstanding | B28: =DCF!B17 -> 405.82
A29: Implied Price / Share | B29: =B27/B28 -> 1234.7531

Sheet Output
A1: INFOSYS — VALUATION SUMMARY
A2: Valuation Date: 10-Sep-2026
A3: Units: ₹ crore unless otherwise stated
A5: Valuation Snapshot | C5: Upside / (Downside) | G5: Analyst Takeaways
A6: Current Share Price | B6: =Inputs!B18 -> 1036.5 | C6: =0 -> 0 | G6: Valuation View | H6: Base-case DCF indicates moderate upside, with an intrinsic value of approximately ₹1,173/share versus the current price of ₹1,036.50.
A7: DCF Intrinsic Value / Share | B7: =DCF!B18 -> 1173.1027 | C7: =B7/B6-1 -> 0.13179231 | G7: Relative Valuation | H7: Infosys trades at a discount to peers on both P/E and EV/EBITDA, with the discount more pronounced on P/E.
A8: P/E Implied Value / Share | B8: =Comps!E20 -> 1269.8544 | C8: =B8/B6-1 -> 0.22513691 | G8: Key Sensitivity | H8: DCF valuation is highly sensitive to WACC and terminal growth, with the tested range spanning approximately ₹957–₹1,563/share.
A9: EV/EBITDA Implied Value / Share | B9: =Comps!B29 -> 1234.7531 | C9: =B9/B6-1 -> 0.19127168 | G9: Key Risk | H9: The valuation depends on assumptions around revenue growth, operating margins, capital expenditure, working capital investment and long-term growth.
A12: Key DCF Assumptions
A13: WACC | B13: =DCF!B9 -> 0.10885
A14: Terminal Growth Rate | B14: =DCF!B10 -> 0.04
A15: FY2027 Revenue Growth | B15: =Inputs!B7 -> 0.03
A16: FY2031 Revenue Growth | B16: =Inputs!F7 -> 0.06
A17: EBITDA Margin | B17: =Inputs!B8 -> 0.235
A18: Tax Rate | B18: =Inputs!B10 -> 0.25
A21: Relative Valuation
A22: Infosys P/E | B22: =Comps!B12 -> 13.887759
A23: Peer Median P/E | B23: =Comps!B15 -> 17.014406
A24: P/E Premium / (Discount) | B24: =B22/B23-1 -> -0.18376469
A25: Infosys EV/EBITDA | B25: =Comps!B13 -> 9.3720379
A26: Peer Median EV/EBITDA | B26: =Comps!B16 -> 10.745918
A27: EV/EBITDA Premium / (Discount) | B27: =B25/B26-1 -> -0.12785132
A30: DCF Sensitivity — Key Scenarios
A31: Scenario | B31: WACC | C31: Terminal Growth | D31: Implied Value / Share | E31: Upside / (Downside)
A32: Conservative Case | B32: =DCF!A40 -> 0.11885 | C32: =DCF!B37 -> 0.03 | D32: =DCF!B40 -> 957.49371 | E32: =D32/$B$6-1 -> -0.076224115
A33: Base Case | B33: =DCF!A39 -> 0.10885 | C33: =DCF!C37 -> 0.04 | D33: =DCF!C39 -> 1173.1027 | E33: =D33/$B$6-1 -> 0.13179231
A34: Optimistic Case | B34: =DCF!A38 -> 0.09885 | C34: =DCF!D37 -> 0.05 | D34: =DCF!D38 -> 1563.2346 | E34: =D34/$B$6-1 -> 0.50818579

Sheet Valuation_Summary
A1: INFOSYS — INVESTMENT SUMMARY
A2: Valuation Date: 10-Sep-2026
A3: Units: ₹ crore unless otherwise stated | Share price and implied valuation in ₹/share
A5: Valuation Snapshot | C5: Upside / (Downside) | E5: DCF SENSITIVITY — Key Scenarios
A6: Current Share Price | B6: =Inputs!B18 -> 1036.5 | C6: =0 -> 0 | E6: Scenario | F6: WACC | G6: Terminal Growth | H6: Implied Value / Share | I6: Upside / (Downside)
A7: DCF Intrinsic Value / Share | B7: =DCF!B18 -> 1173.1027 | C7: =B7/B6-1 -> 0.13179231 | E7: Conservative Case | F7: =Output!B32 -> 0.11885 | G7: =Output!C32 -> 0.03 | H7: =Output!D32 -> 957.49371 | I7: =Output!E32 -> -0.076224115
A8: P/E Implied Value / Share | B8: =Comps!E20 -> 1269.8544 | C8: =B8/B6-1 -> 0.22513691 | E8: Base Case | F8: =Output!B33 -> 0.10885 | G8: =Output!C33 -> 0.04 | H8: =Output!D33 -> 1173.1027 | I8: =Output!E33 -> 0.13179231
A9: EV/EBITDA Implied Value / Share | B9: =Comps!B29 -> 1234.7531 | C9: =B9/B6-1 -> 0.19127168 | E9: Optimistic Case | F9: =Output!B34 -> 0.09885 | G9: =Output!C34 -> 0.05 | H9: =Output!D34 -> 1563.2346 | I9: =Output!E34 -> 0.50818579
A27: Analyst Takeaways
A28: =Output!G6 -> Valuation View | B28: =Output!H6 -> Base-case DCF indicates moderate upside, with an intrinsic value of approximately ₹1,173/share versus the current price of ₹1,036.50.
A29: =Output!G7 -> Relative Valuation | B29: =Output!H7 -> Infosys trades at a discount to peers on both P/E and EV/EBITDA, with the discount more pronounced on P/E.
A30: =Output!G8 -> Key Sensitivity | B30: =Output!H8 -> DCF valuation is highly sensitive to WACC and terminal growth, with the tested range spanning approximately ₹957–₹1,563/share.
A31: =Output!G9 -> Key Risk | B31: =Output!H9 -> The valuation depends on assumptions around revenue growth, operating margins, capital expenditure, working capital investment and long-term growth.

Sheet Sources
A1: INFOSYS — SOURCES & METHODOLOGY
A2: Units: ₹ crore unless otherwise stated
A4: Item | B4: Source | C4: Date / Period | D4: Used For
A5: Infosys Annual Report | B5: Infosys Investor Relations | C5: FY2026 | D5: Historical financials, cash & investments, debt
A6: Infosys Q1 FY27 Results | B6: Infosys Investor Relations | C6: Q1 FY2027 | D6: LTM financials, latest share count, guidance
A7: India 10-Year G-Sec Yield | B7: Market data source | C7: 46275 | D7: Risk-free rate
A8: Infosys Beta | B8: Economic Times | C8: 46275 | D8: CAPM
A9: India Equity Risk Premium | B9: Aswath Damodaran | C9: Jan-2026 dataset | D9: Equity risk premium
A10: Peer Market Data | B10: Market-data provider | C10: 46275 | D10: Share price, market cap, enterprise value
A11: Peer LTM Financials | B11: Market-data provider / company filings | C11: Latest available | D11: Revenue, EBITDA, net income
A14: Methodology & Key Notes
A16: Item | B16: Note
A17: DCF | B17: FCFF discounted using WACC; terminal value calculated using the Gordon Growth Method.
A18: Forecast | B18: FY2027 revenue growth uses the upper end of Infosys' revised 1.5%–3.0% constant-currency guidance; FY2028–FY2031 are analyst assumptions.
A19: Terminal Growth | B19: 4.00% normalized long-term growth assumption; not company guidance.
A20: WACC | B20: CAPM-based cost of equity; Infosys has no meaningful debt, resulting in a 100% equity weight.
A21: Comps | B21: Peer median excludes Infosys.
A22: P/E | B22: Peer P/E applied to Infosys LTM net income to derive implied equity value.
A23: EV/EBITDA | B23: Peer EV/EBITDA applied to Infosys LTM EBITDA; implied EV bridged to equity value using cash & investments and debt.
A24: Valuation Date | B24: 10-Sep-2026.
A25: Units | B25: ₹ crore unless otherwise stated; share price in ₹/share; shares in crore.

Sheet Chart_data
A2: Year | B2: Historical Revenue | C2: Forecast Revenue
A3: FY2022 | B3: =Historicals!B5 -> 121641
A4: FY2023 | B4: =Historicals!C5 -> 146767
A5: FY2024 | B5: =Historicals!D5 -> 153670
A6: FY2025 | B6: =Historicals!E5 -> 162990
A7: FY2026 | B7: =Historicals!F5 -> 178650 | C7: =Historicals!F5 -> 178650
A8: FY2027 | C8: =Forecast!B6 -> 184009.5
A9: FY2028 | C9: =Forecast!C6 -> 193209.98
A10: FY2029 | C10: =Forecast!D6 -> 204802.57
A11: FY2030 | C11: =Forecast!E6 -> 217090.73
A12: FY2031 | C12: =Forecast!F6 -> 230116.17
A20: Year | B20: FCFF
A21: FY2027 | B21: =Forecast!B16 -> 28176.455
A22: FY2028 | B22: =Forecast!C16 -> 29585.277
A23: FY2029 | B23: =Forecast!D16 -> 31360.394
A24: FY2030 | B24: =Forecast!E16 -> 33242.018
A25: FY2031 | B25: =Forecast!F16 -> 35236.539
